{
  "book": {
    "abbrev": {
      "pt": "sl",
      "en": "ps"
    },
    "name": "Salmos",
    "author": "David, Mois\u00e9s, Salom\u00e3o",
    "group": "Po\u00e9ticos",
    "version": "nvi"
  },
  "chapter": {
    "number": 122,
    "verses": 9
  },
  "verses": [
    {
      "number": 1,
      "text": "Alegrei-me com os que me disseram: \"Vamos \u00e0 casa do Senhor! \""
    },
    {
      "number": 2,
      "text": "Nossos p\u00e9s j\u00e1 se encontram dentro de suas portas, \u00f3 Jerusal\u00e9m!"
    },
    {
      "number": 3,
      "text": "Jerusal\u00e9m est\u00e1 constru\u00edda como cidade firmemente estabelecida."
    },
    {
      "number": 4,
      "text": "Para l\u00e1 sobem as tribos do Senhor, para dar gra\u00e7as ao Senhor, conforme o mandamento dado a Israel."
    },
    {
      "number": 5,
      "text": "L\u00e1 est\u00e3o os tribunais de justi\u00e7a, os tribunais da casa real de Davi."
    },
    {
      "number": 6,
      "text": "Orem pela paz de Jerusal\u00e9m: \"Vivam em seguran\u00e7a aqueles que te amam!"
    },
    {
      "number": 7,
      "text": "Haja paz dentro dos teus muros e seguran\u00e7a nas tuas cidadelas! \""
    },
    {
      "number": 8,
      "text": "Em favor de meus irm\u00e3os e amigos, direi: \"Paz seja com voc\u00ea! \""
    },
    {
      "number": 9,
      "text": "Em favor da casa do Senhor, nosso Deus, buscarei o seu bem."
    }
  ]
}